mqtt_recorder/__init__.py
mqtt_recorder/__main__.py
mqtt_recorder/recorder.py
mqtt_recorder-1.4.0.dist-info/LICENSE
mqtt_recorder-1.4.0.dist-info/METADATA
mqtt_recorder-1.4.0.dist-info/WHEEL
mqtt_recorder-1.4.0.dist-info/entry_points.txt
mqtt_recorder-1.4.0.dist-info/top_level.txt
mqtt_recorder-1.4.0.dist-info/RECORD
