Metadata-Version: 2.1
Name: mqtt-recorder
Version: 1.4.0
Summary: MQTT recorder tool
Author: RPDSWTK
License: MIT License
Project-URL: Homepage, https://github.com/rpdswtk/mqtt_recorder
Keywords: feed,reader,tutorial
Requires-Python: >=3.7
License-File: LICENSE
Requires-Dist: paho-mqtt>=2.0.0
Requires-Dist: tqdm>=4.65.0
